zeroquant/__init__.py
zeroquant/abis.py
zeroquant/client.py
zeroquant/exceptions.py
zeroquant/models.py
zeroquant/retry.py
zeroquant/exchange_adapters/__init__.py
zeroquant/exchange_adapters/base_adapter.py
zeroquant/exchange_adapters/binance.py
zeroquant/exchange_adapters/coinbase.py
zeroquant/exchange_adapters/kraken.py
zeroquant/exchange_adapters/router.py
zeroquant/exchange_adapters/types.py
zeroquant/intents/__init__.py
zeroquant/intents/swap.py
zeroquant/langchain/__init__.py
zeroquant/langchain/tools.py
zeroquant/orders/__init__.py
zeroquant/orders/manager.py
zeroquant/orders/models.py
zeroquant/orders/mvo.py
zeroquant/positions/__init__.py
zeroquant/positions/models.py
zeroquant/positions/tracker.py
zeroquant/services/__init__.py
zeroquant/services/price.py
zeroquant/tee/__init__.py
zeroquant/tee/client.py
zeroquant/tee/intel_tdx.py
zeroquant/tee/models.py
zeroquant_sdk-0.3.3.dist-info/METADATA
zeroquant_sdk-0.3.3.dist-info/WHEEL
zeroquant_sdk-0.3.3.dist-info/top_level.txt
zeroquant_sdk-0.3.3.dist-info/RECORD
