Metadata-Version: 2.4
Name: zeroquant-sdk
Version: 0.3.3
Summary: Python SDK for ZeroQuant agentic DeFi vaults
Author: ZeroQuant Team
License: MIT
Keywords: zeroquant,defi,ethereum,ai,agents,web3
Requires-Python: >=3.10
Requires-Dist: web3[async]>=6.0.0
Requires-Dist: eth-account>=0.10.0
Requires-Dist: httpx>=0.25.0
Requires-Dist: pydantic>=2.0.0
Requires-Dist: tenacity>=8.2.0
Provides-Extra: langchain
Requires-Dist: langchain>=0.1.0; extra == "langchain"
Provides-Extra: dev
Requires-Dist: pytest>=7.4.0; extra == "dev"
Requires-Dist: pytest-asyncio>=0.21.0; extra == "dev"
Requires-Dist: black>=23.0.0; extra == "dev"
Requires-Dist: mypy>=1.5.0; extra == "dev"
Requires-Dist: ruff>=0.1.0; extra == "dev"
